solace_ai_connector_slack/__init__.py
solace_ai_connector_slack/components/__init__.py
solace_ai_connector_slack/components/slack_base.py
solace_ai_connector_slack/components/slack_input.py
solace_ai_connector_slack/components/slack_output.py
solace_ai_connector_slack-0.0.2.dist-info/METADATA
solace_ai_connector_slack-0.0.2.dist-info/WHEEL
solace_ai_connector_slack-0.0.2.dist-info/licenses/LICENSE
solace_ai_connector_slack-0.0.2.dist-info/RECORD
